{"chunk_definitions":[{"chunk_id":"csetup_chunk","chunk_label":"setup","document_id":"244FC213","expansion_state":0,"options":{"engine":"r","include":false,"label":"setup"},"row":10,"row_count":1,"visible":true},{"chunk_id":"csetup_chunk","chunk_label":"unnamed-chunk-1","document_id":"244FC213","expansion_state":0,"options":{"engine":"r","include":false,"label":"setup"},"row":27,"row_count":1,"visible":true},{"chunk_id":"c8rpd6cbdze78","chunk_label":"unnamed-chunk-2","document_id":"244FC213","expansion_state":0,"options":{"engine":"r","label":"unnamed-chunk-1"},"row":43,"row_count":1,"visible":true},{"chunk_id":"c17soc5lw0kyx","chunk_label":"unnamed-chunk-3","document_id":"244FC213","expansion_state":0,"options":{"engine":"r","label":"unnamed-chunk-2"},"row":49,"row_count":1,"visible":true},{"chunk_id":"cyd0uvq4zqcl3","chunk_label":"unnamed-chunk-4","document_id":"244FC213","expansion_state":0,"options":{"engine":"r","label":"unnamed-chunk-3"},"row":55,"row_count":1,"visible":true},{"chunk_id":"cdyvnbh6470fs","chunk_label":"unnamed-chunk-5","document_id":"244FC213","expansion_state":0,"options":{"engine":"r","label":"unnamed-chunk-4"},"row":60,"row_count":1,"visible":true},{"chunk_id":"co26pkz2mq6jl","chunk_label":"unnamed-chunk-6","document_id":"244FC213","expansion_state":0,"options":{"engine":"r","label":"unnamed-chunk-35"},"row":65,"row_count":1,"visible":true},{"chunk_id":"cvonvv8hxuuu9","chunk_label":"unnamed-chunk-8","document_id":"244FC213","expansion_state":0,"options":{"engine":"r","label":"unnamed-chunk-5"},"row":133,"row_count":1,"visible":true},{"chunk_id":"cbk3gx0chk9qa","chunk_label":"unnamed-chunk-9","document_id":"244FC213","expansion_state":0,"options":{"engine":"r","label":"unnamed-chunk-8"},"row":147,"row_count":1,"visible":true},{"chunk_id":"cgyand4z2t0h4","chunk_label":"unnamed-chunk-10","document_id":"244FC213","expansion_state":0,"options":{"engine":"r","label":"unnamed-chunk-18"},"row":182,"row_count":1,"visible":true},{"chunk_id":"cjvuopvbt4iup","chunk_label":"unnamed-chunk-11","document_id":"244FC213","expansion_state":0,"options":{"engine":"r","label":"unnamed-chunk-20"},"row":195,"row_count":1,"visible":true},{"chunk_id":"ckzohs7odgz69","chunk_label":"unnamed-chunk-12","document_id":"244FC213","expansion_state":0,"options":{"engine":"r","label":"unnamed-chunk-36"},"row":227,"row_count":1,"visible":true},{"chunk_id":"chhhjsnpgc619","chunk_label":"unnamed-chunk-13","document_id":"244FC213","expansion_state":0,"options":{"engine":"r","label":"unnamed-chunk-53"},"row":260,"row_count":1,"visible":true},{"chunk_id":"c7j0mak58rzp2","chunk_label":"unnamed-chunk-14","document_id":"244FC213","expansion_state":0,"options":{"engine":"r","label":"unnamed-chunk-54"},"row":299,"row_count":1,"visible":true},{"chunk_id":"cj7uabnm7f0j3","chunk_label":"unnamed-chunk-15","document_id":"244FC213","expansion_state":0,"options":{"engine":"r","label":"unnamed-chunk-56"},"row":306,"row_count":1,"visible":true},{"chunk_id":"cd7ssqsr5rgr0","chunk_label":"unnamed-chunk-16","document_id":"244FC213","expansion_state":0,"options":{"engine":"r","label":"unnamed-chunk-57"},"row":313,"row_count":1,"visible":true},{"chunk_id":"c7gpv07zxmpa2","chunk_label":"unnamed-chunk-17","document_id":"244FC213","expansion_state":0,"options":{"engine":"r","label":"unnamed-chunk-58"},"row":323,"row_count":1,"visible":true},{"chunk_id":"c5mkh9c0xo0dm","chunk_label":"unnamed-chunk-18","document_id":"244FC213","expansion_state":0,"options":{"engine":"r","label":"unnamed-chunk-59"},"row":331,"row_count":1,"visible":true},{"chunk_id":"cbdibo3mewf01","chunk_label":"unnamed-chunk-19","document_id":"244FC213","expansion_state":0,"options":{"engine":"r","label":"unnamed-chunk-60"},"row":338,"row_count":1,"visible":true},{"chunk_id":"c24s2vk9gz6pc","chunk_label":"unnamed-chunk-20","document_id":"244FC213","expansion_state":0,"options":{"engine":"r","label":"unnamed-chunk-61"},"row":374,"row_count":1,"visible":true},{"chunk_id":"co1i2it77ldbx","chunk_label":"unnamed-chunk-21","document_id":"244FC213","expansion_state":0,"options":{"engine":"r","label":"unnamed-chunk-63"},"row":395,"row_count":1,"visible":true},{"chunk_id":"cq9het0uii0ga","chunk_label":"unnamed-chunk-22","document_id":"244FC213","expansion_state":0,"options":{"engine":"r","label":"unnamed-chunk-88"},"row":445,"row_count":1,"visible":true}],"chunk_rendered_width":649,"default_chunk_options":{"echo":false,"error":false},"doc_write_time":1555078212,"working_dir":null}